background_rm/__init__.py
background_rm/compiled.py
background_rm/tests/test_data/.DS_Store
background_rm/tests/test_data/bg.tif
background_rm/tests/test_data/im.tif
background_rm-0.1.3.dist-info/METADATA
background_rm-0.1.3.dist-info/WHEEL
background_rm-0.1.3.dist-info/top_level.txt
background_rm-0.1.3.dist-info/RECORD
