Metadata-Version: 2.1
Name: background-rm
Version: 0.1.3
Summary: remove background from images
Home-page: https://github.com/impact27/background_rm
Author: Quentin Peter
Author-email: qaep2@cam.ac.uk
License: GPl v3
Keywords: background removal microfluidics
Platform: UNKNOWN
Classifier: Development Status :: 4 - Beta
Classifier: License :: OSI Approved :: GNU General Public License v3 or later (GPLv3+)
Classifier: Programming Language :: Python :: 3 :: Only
Classifier: Topic :: Scientific/Engineering
Requires-Dist: numpy
Requires-Dist: scipy
Requires-Dist: opencv-python
Requires-Dist: registrator
